scrubby/__init__.py
scrubby/cli.py
scrubby/db/__init__.py
scrubby/db/entity/__init__.py
scrubby/db/entity/column.py
scrubby/db/entity/table.py
scrubby/db/provider/__init__.py
scrubby/db/provider/null_provider.py
scrubby/db/provider/postgres_provider.py
scrubby/db/provider/provider.py
scrubby/db/provider/provider_factory.py
scrubby/db/provider/transaction_scope.py
scrubby/definition/__init__.py
scrubby/definition/definition.py
scrubby/definition/definition_builder.py
scrubby/definition/definition_file_reader.py
scrubby/definition/table_definition.py
scrubby/definition/table_field_definition.py
scrubby/execution/__init__.py
scrubby/execution/clear_table_column_execution_step.py
scrubby/execution/clear_table_execution_step.py
scrubby/execution/execution_plan.py
scrubby/execution/execution_planner.py
scrubby/execution/execution_step.py
scrubby-0.1.13.dist-info/DESCRIPTION.rst
scrubby-0.1.13.dist-info/METADATA
scrubby-0.1.13.dist-info/RECORD
scrubby-0.1.13.dist-info/WHEEL
scrubby-0.1.13.dist-info/entry_points.txt
scrubby-0.1.13.dist-info/metadata.json
scrubby-0.1.13.dist-info/top_level.txt
